{
  "SOL_Holdout": [
    {
      "sharpe_d": -0.16,
      "return": -13.1,
      "max_dd": -26.5,
      "worst_day": -5.33,
      "wr": 41.8,
      "pf": 1.02,
      "mcl": 11,
      "tpm": 16.0,
      "trades": 416,
      "worst_mo": -11.73,
      "mean_mo": -0.24,
      "cost_mo": 4.8,
      "entry_tf": "4h",
      "entry_ma": 12
    },
    {
      "sharpe_d": -0.3,
      "return": -18.9,
      "max_dd": -39.7,
      "worst_day": -3.53,
      "wr": 41.9,
      "pf": 1.01,
      "mcl": 9,
      "tpm": 23.4,
      "trades": 609,
      "worst_mo": -11.76,
      "mean_mo": -0.52,
      "cost_mo": 7.03,
      "entry_tf": "4h",
      "entry_ma": 6
    },
    {
      "sharpe_d": -0.08,
      "return": -8.8,
      "max_dd": -23.4,
      "worst_day": -4.87,
      "wr": 42.1,
      "pf": 1.03,
      "mcl": 9,
      "tpm": 12.6,
      "trades": 328,
      "worst_mo": -7.75,
      "mean_mo": 0.03,
      "cost_mo": 3.78,
      "entry_tf": "4h",
      "entry_ma": 18
    },
    {
      "sharpe_d": -0.83,
      "return": -49.8,
      "max_dd": -64.3,
      "worst_day": -7.95,
      "wr": 37.0,
      "pf": 0.94,
      "mcl": 14,
      "tpm": 41.3,
      "trades": 1073,
      "worst_mo": -19.51,
      "mean_mo": -2.1,
      "cost_mo": 12.39,
      "entry_tf": "1h",
      "entry_ma": 24
    },
    {
      "sharpe_d": -0.45,
      "return": -28.5,
      "max_dd": -46.0,
      "worst_day": -6.28,
      "wr": 36.3,
      "pf": 0.99,
      "mcl": 13,
      "tpm": 29.2,
      "trades": 758,
      "worst_mo": -17.16,
      "mean_mo": -0.92,
      "cost_mo": 8.75,
      "entry_tf": "1h",
      "entry_ma": 48
    },
    {
      "sharpe_d": -0.32,
      "return": -21.4,
      "max_dd": -29.1,
      "worst_day": -6.05,
      "wr": 33.2,
      "pf": 1.0,
      "mcl": 14,
      "tpm": 22.6,
      "trades": 587,
      "worst_mo": -14.79,
      "mean_mo": -0.55,
      "cost_mo": 6.77,
      "entry_tf": "1h",
      "entry_ma": 72
    },
    {
      "sharpe_d": -0.21,
      "return": -17.5,
      "max_dd": -31.1,
      "worst_day": -5.53,
      "wr": 34.9,
      "pf": 1.0,
      "mcl": 12,
      "tpm": 19.4,
      "trades": 504,
      "worst_mo": -10.92,
      "mean_mo": -0.26,
      "cost_mo": 5.82,
      "entry_tf": "1h",
      "entry_ma": 120
    }
  ],
  "SOL_2022": [
    {
      "sharpe_d": 0.05,
      "return": -5.1,
      "max_dd": -32.9,
      "worst_day": -12.18,
      "wr": 35.9,
      "pf": 1.01,
      "mcl": 16,
      "tpm": 17.5,
      "trades": 192,
      "worst_mo": -13.52,
      "mean_mo": -0.64,
      "cost_mo": 5.24,
      "entry_tf": "4h",
      "entry_ma": 12
    },
    {
      "sharpe_d": -0.29,
      "return": -18.9,
      "max_dd": -43.1,
      "worst_day": -6.68,
      "wr": 38.8,
      "pf": 0.92,
      "mcl": 9,
      "tpm": 26.0,
      "trades": 286,
      "worst_mo": -14.82,
      "mean_mo": -1.74,
      "cost_mo": 7.8,
      "entry_tf": "4h",
      "entry_ma": 6
    },
    {
      "sharpe_d": 0.17,
      "return": 0.3,
      "max_dd": -25.5,
      "worst_day": -12.15,
      "wr": 34.7,
      "pf": 1.04,
      "mcl": 7,
      "tpm": 13.4,
      "trades": 147,
      "worst_mo": -12.15,
      "mean_mo": -0.27,
      "cost_mo": 4.01,
      "entry_tf": "4h",
      "entry_ma": 18
    },
    {
      "sharpe_d": 0.13,
      "return": -0.9,
      "max_dd": -35.6,
      "worst_day": -7.2,
      "wr": 37.3,
      "pf": 1.12,
      "mcl": 12,
      "tpm": 43.9,
      "trades": 483,
      "worst_mo": -11.78,
      "mean_mo": -0.34,
      "cost_mo": 13.17,
      "entry_tf": "1h",
      "entry_ma": 24
    },
    {
      "sharpe_d": 0.23,
      "return": 2.9,
      "max_dd": -32.2,
      "worst_day": -12.52,
      "wr": 34.8,
      "pf": 1.14,
      "mcl": 10,
      "tpm": 30.3,
      "trades": 333,
      "worst_mo": -14.88,
      "mean_mo": -0.04,
      "cost_mo": 9.08,
      "entry_tf": "1h",
      "entry_ma": 48
    },
    {
      "sharpe_d": 0.63,
      "return": 18.8,
      "max_dd": -20.6,
      "worst_day": -10.68,
      "wr": 37.6,
      "pf": 1.33,
      "mcl": 9,
      "tpm": 22.3,
      "trades": 245,
      "worst_mo": -10.89,
      "mean_mo": 1.29,
      "cost_mo": 6.68,
      "entry_tf": "1h",
      "entry_ma": 72
    },
    {
      "sharpe_d": 0.88,
      "return": 28.9,
      "max_dd": -18.7,
      "worst_day": -10.37,
      "wr": 37.0,
      "pf": 1.47,
      "mcl": 9,
      "tpm": 15.0,
      "trades": 165,
      "worst_mo": -9.45,
      "mean_mo": 1.49,
      "cost_mo": 4.51,
      "entry_tf": "1h",
      "entry_ma": 120
    }
  ],
  "BTC_Holdout": [
    {
      "sharpe_d": -0.29,
      "return": -12.0,
      "max_dd": -25.4,
      "worst_day": -3.88,
      "wr": 42.4,
      "pf": 1.02,
      "mcl": 9,
      "tpm": 16.8,
      "trades": 436,
      "worst_mo": -8.72,
      "mean_mo": -0.23,
      "cost_mo": 5.03,
      "entry_tf": "4h",
      "entry_ma": 12
    },
    {
      "sharpe_d": -0.43,
      "return": -15.6,
      "max_dd": -27.5,
      "worst_day": -3.08,
      "wr": 42.1,
      "pf": 1.04,
      "mcl": 9,
      "tpm": 24.7,
      "trades": 642,
      "worst_mo": -6.44,
      "mean_mo": -0.48,
      "cost_mo": 7.41,
      "entry_tf": "4h",
      "entry_ma": 6
    },
    {
      "sharpe_d": -0.01,
      "return": -3.2,
      "max_dd": -20.2,
      "worst_day": -3.42,
      "wr": 39.8,
      "pf": 1.11,
      "mcl": 7,
      "tpm": 12.7,
      "trades": 329,
      "worst_mo": -5.73,
      "mean_mo": -0.03,
      "cost_mo": 3.8,
      "entry_tf": "4h",
      "entry_ma": 18
    },
    {
      "sharpe_d": -0.88,
      "return": -29.6,
      "max_dd": -35.8,
      "worst_day": -2.94,
      "wr": 40.9,
      "pf": 1.04,
      "mcl": 12,
      "tpm": 43.8,
      "trades": 1138,
      "worst_mo": -7.0,
      "mean_mo": -0.95,
      "cost_mo": 13.14,
      "entry_tf": "1h",
      "entry_ma": 24
    },
    {
      "sharpe_d": -0.8,
      "return": -28.2,
      "max_dd": -32.2,
      "worst_day": -4.17,
      "wr": 34.7,
      "pf": 0.97,
      "mcl": 12,
      "tpm": 29.5,
      "trades": 767,
      "worst_mo": -8.96,
      "mean_mo": -0.93,
      "cost_mo": 8.86,
      "entry_tf": "1h",
      "entry_ma": 48
    },
    {
      "sharpe_d": -0.31,
      "return": -12.6,
      "max_dd": -22.2,
      "worst_day": -3.68,
      "wr": 33.5,
      "pf": 1.07,
      "mcl": 13,
      "tpm": 22.3,
      "trades": 579,
      "worst_mo": -6.65,
      "mean_mo": -0.3,
      "cost_mo": 6.68,
      "entry_tf": "1h",
      "entry_ma": 72
    },
    {
      "sharpe_d": -0.5,
      "return": -19.2,
      "max_dd": -27.1,
      "worst_day": -3.91,
      "wr": 32.0,
      "pf": 0.97,
      "mcl": 13,
      "tpm": 18.7,
      "trades": 485,
      "worst_mo": -8.62,
      "mean_mo": -0.67,
      "cost_mo": 5.6,
      "entry_tf": "1h",
      "entry_ma": 120
    }
  ],
  "BTC_2022": [
    {
      "sharpe_d": -0.4,
      "return": -8.2,
      "max_dd": -13.7,
      "worst_day": -2.9,
      "wr": 39.2,
      "pf": 0.95,
      "mcl": 7,
      "tpm": 18.1,
      "trades": 199,
      "worst_mo": -4.42,
      "mean_mo": -0.62,
      "cost_mo": 5.44,
      "entry_tf": "4h",
      "entry_ma": 12
    },
    {
      "sharpe_d": -0.45,
      "return": -8.7,
      "max_dd": -13.1,
      "worst_day": -2.97,
      "wr": 42.1,
      "pf": 1.0,
      "mcl": 7,
      "tpm": 25.9,
      "trades": 285,
      "worst_mo": -4.78,
      "mean_mo": -0.66,
      "cost_mo": 7.79,
      "entry_tf": "4h",
      "entry_ma": 6
    },
    {
      "sharpe_d": 0.06,
      "return": -0.3,
      "max_dd": -9.7,
      "worst_day": -2.96,
      "wr": 36.9,
      "pf": 1.08,
      "mcl": 7,
      "tpm": 14.3,
      "trades": 157,
      "worst_mo": -3.66,
      "mean_mo": -0.02,
      "cost_mo": 4.3,
      "entry_tf": "4h",
      "entry_ma": 18
    },
    {
      "sharpe_d": -0.89,
      "return": -17.7,
      "max_dd": -20.3,
      "worst_day": -4.26,
      "wr": 37.9,
      "pf": 0.98,
      "mcl": 16,
      "tpm": 48.5,
      "trades": 533,
      "worst_mo": -4.72,
      "mean_mo": -1.59,
      "cost_mo": 14.54,
      "entry_tf": "1h",
      "entry_ma": 24
    },
    {
      "sharpe_d": -0.88,
      "return": -17.6,
      "max_dd": -22.2,
      "worst_day": -3.87,
      "wr": 35.4,
      "pf": 0.91,
      "mcl": 14,
      "tpm": 34.5,
      "trades": 379,
      "worst_mo": -5.6,
      "mean_mo": -1.71,
      "cost_mo": 10.34,
      "entry_tf": "1h",
      "entry_ma": 48
    },
    {
      "sharpe_d": -0.54,
      "return": -11.4,
      "max_dd": -17.8,
      "worst_day": -3.46,
      "wr": 34.3,
      "pf": 0.94,
      "mcl": 14,
      "tpm": 25.5,
      "trades": 280,
      "worst_mo": -6.35,
      "mean_mo": -1.25,
      "cost_mo": 7.65,
      "entry_tf": "1h",
      "entry_ma": 72
    },
    {
      "sharpe_d": -0.18,
      "return": -5.2,
      "max_dd": -14.0,
      "worst_day": -3.16,
      "wr": 35.3,
      "pf": 1.01,
      "mcl": 9,
      "tpm": 18.8,
      "trades": 207,
      "worst_mo": -4.71,
      "mean_mo": -0.67,
      "cost_mo": 5.66,
      "entry_tf": "1h",
      "entry_ma": 120
    }
  ]
}